amr2h5/__init__.py
amr2h5/converter.py
amr2h5/reader.py
amr2h5-0.0.3.dist-info/METADATA
amr2h5-0.0.3.dist-info/WHEEL
amr2h5-0.0.3.dist-info/licenses/LICENSE.txt
amr2h5-0.0.3.dist-info/RECORD
