Metadata-Version: 2.1
Name: amr2h5
Version: 0.0.3
Summary: A converter from AMR Block data (BoxLib) to H5 covered grids
Project-URL: Homepage, https://github.com/olivecha/amr2h5/
Project-URL: Bug Tracker, https://github.com/olivecha/amr2h5/issues
Author-email: Olivier Chabot <olivier.chabot@polymtl.ca>
License-File: LICENSE.txt
Classifier: License :: OSI Approved :: MIT License
Classifier: Operating System :: OS Independent
Classifier: Programming Language :: Python :: 3
Requires-Python: >=3.6
Requires-Dist: h5py
Requires-Dist: matplotlib
Requires-Dist: numpy
Requires-Dist: yt
Provides-Extra: test
Requires-Dist: pytest; extra == 'test'
